trytond/modules/cashbook_planner/README.rst
trytond/modules/cashbook_planner/__init__.py
trytond/modules/cashbook_planner/cashbook.py
trytond/modules/cashbook_planner/cashbook.xml
trytond/modules/cashbook_planner/config.py
trytond/modules/cashbook_planner/config.xml
trytond/modules/cashbook_planner/cron.py
trytond/modules/cashbook_planner/cron.xml
trytond/modules/cashbook_planner/group.xml
trytond/modules/cashbook_planner/ir.py
trytond/modules/cashbook_planner/menu.xml
trytond/modules/cashbook_planner/message.xml
trytond/modules/cashbook_planner/nextrun.py
trytond/modules/cashbook_planner/nextrun.xml
trytond/modules/cashbook_planner/planner.py
trytond/modules/cashbook_planner/planner.xml
trytond/modules/cashbook_planner/tryton.cfg
trytond/modules/cashbook_planner/versiondep.txt
trytond/modules/cashbook_planner/locale/de.po
trytond/modules/cashbook_planner/locale/en.po
trytond/modules/cashbook_planner/tests/__init__.py
trytond/modules/cashbook_planner/tests/planner.py
trytond/modules/cashbook_planner/tests/test_module.py
trytond/modules/cashbook_planner/view/book_form.xml
trytond/modules/cashbook_planner/view/configuration_form.xml
trytond/modules/cashbook_planner/view/nextrun_form.xml
trytond/modules/cashbook_planner/view/nextrun_list.xml
trytond/modules/cashbook_planner/view/planner_form.xml
trytond/modules/cashbook_planner/view/planner_list.xml
mds_cashbook_planner-7.0.8.dist-info/LICENSE
mds_cashbook_planner-7.0.8.dist-info/METADATA
mds_cashbook_planner-7.0.8.dist-info/WHEEL
mds_cashbook_planner-7.0.8.dist-info/entry_points.txt
mds_cashbook_planner-7.0.8.dist-info/top_level.txt
mds_cashbook_planner-7.0.8.dist-info/RECORD
